decontext/__init__.py
decontext/cache.py
decontext/data_types.py
decontext/logging.py
decontext/model.py
decontext/pipeline.py
decontext/py.typed
decontext/template.py
decontext/utils.py
decontext/step/qa.py
decontext/step/qgen.py
decontext/step/step.py
decontext/step/synth.py
decontext/templates/__init__.py
decontext/templates/qa_fulltext.yaml
decontext/templates/qa_retrieval.yaml
decontext/templates/qgen.yaml
decontext/templates/synth.yaml
decontext-0.1.7.dist-info/METADATA
decontext-0.1.7.dist-info/WHEEL
decontext-0.1.7.dist-info/top_level.txt
decontext-0.1.7.dist-info/RECORD
