Metadata-Version: 2.1
Name: decontext
Version: 0.1.7
Summary: Pipeline for decontextualization of scientific snippets.
Author-email: Allen Institute for Artificial Intelligence <contact@allenai.org>, Benjamin Newman <bnewmancommercial@gmail.com>, Luca Soldaini <luca@soldaini.net>, Kyle Lo <kylel@allenai.org>
Maintainer-email: Benjamin Newman <bnewmancommercial@gmail.com>
License: Apache-2.0
Project-URL: Homepage, https://github.com/bnewm0609/qa-decontextualization
Project-URL: Repository, https://github.com/bnewm0609/qa-decontextualization
Project-URL: Bug Tracker, https://github.com/bnewm0609/qa-decontextualization/issues
Classifier: Development Status :: 4 - Beta
Classifier: License :: OSI Approved :: Apache Software License
Classifier: Operating System :: OS Independent
Classifier: Programming Language :: Python :: 3
Classifier: Topic :: Scientific/Engineering :: Artificial Intelligence
Classifier: Topic :: Software Development :: Libraries :: Python Modules
Classifier: Topic :: Utilities
Classifier: Typing :: Typed
Requires-Python: >=3.8
Requires-Dist: anthropic ==0.2.10
Requires-Dist: diskcache ==5.6.1
Requires-Dist: filelock ==3.12.2
Requires-Dist: Jinja2 >=3.1.2
Requires-Dist: shadow-scholar ==0.6.1
Requires-Dist: omegaconf >=2.3.0
Requires-Dist: openai ==0.27.7
Requires-Dist: pydantic <2.0,>=1.10.8
Requires-Dist: tiktoken ==0.4.0
Requires-Dist: numpy >=1.23.2
Requires-Dist: spacy >=3.4.1
Requires-Dist: torch >=1.13.0
Requires-Dist: scikit-learn >=1.1.2
Requires-Dist: transformers >=4.28.0
Requires-Dist: unidecode
Requires-Dist: sentence-transformers >=2.2.2
Requires-Dist: typing-extensions >=4.5.0
Provides-Extra: dev
Requires-Dist: black[jupyter] ==23.7.0 ; extra == 'dev'
Requires-Dist: isort ==5.12.0 ; extra == 'dev'
Requires-Dist: mypy ==1.4.1 ; extra == 'dev'
Requires-Dist: ipython >=8.12.0 ; extra == 'dev'
Requires-Dist: autopep8 ==2.0.2 ; extra == 'dev'
Requires-Dist: flake8 ==6.1.0 ; extra == 'dev'
Requires-Dist: ipdb ==0.13.13 ; extra == 'dev'
Requires-Dist: flake8-pyi ==23.6.0 ; extra == 'dev'
Requires-Dist: Flake8-pyproject ==1.2.3 ; extra == 'dev'
Requires-Dist: pytest ==7.1.3 ; extra == 'dev'
Requires-Dist: pytest-xdist ==3.3.1 ; extra == 'dev'
Requires-Dist: pytest-cov ==4.1.0 ; extra == 'dev'
